flow_vis/__init__.py
flow_vis/flow_vis.py
flow_vis-0.1.dist-info/LICENSE.txt
flow_vis-0.1.dist-info/METADATA
flow_vis-0.1.dist-info/WHEEL
flow_vis-0.1.dist-info/top_level.txt
flow_vis-0.1.dist-info/RECORD
