Metadata-Version: 2.1
Name: flow-vis
Version: 0.1
Summary: Easy optical flow visualisation in Python.
Home-page: https://github.com/tomrunia/OpticalFlow_Visualization
Author: Tom Runia
Author-email: firstname.lastname@gmail.com
License: MIT
Download-URL: https://github.com/tomrunia/OpticalFlow_Visualization/archive/0.1.tar.gz
Keywords: optical flow,visualization,motion
Platform: UNKNOWN
Classifier: Programming Language :: Python :: 3
Classifier: Development Status :: 5 - Production/Stable
Classifier: Intended Audience :: Developers
Classifier: License :: OSI Approved :: MIT License
Requires-Python: >=3.6
Requires-Dist: numpy
